graphius/__init__.py
graphius/graph.py
graphius/visual.py
graphius-0.1.0.dist-info/METADATA
graphius-0.1.0.dist-info/WHEEL
graphius-0.1.0.dist-info/licenses/LICENSE
graphius-0.1.0.dist-info/RECORD
