Metadata-Version: 2.4
Name: graphius
Version: 0.1.0
Summary: A Simple Graph Library with Visualization Support
Project-URL: Source, https://github.com/alperenunlu/graphius
Author: Alperen ÜNLÜ
License-Expression: MIT
License-File: LICENSE
Requires-Python: >=3.10
Requires-Dist: graphviz>=0.21
Requires-Dist: pillow>=11.3.0
